kuoeliassen/core.py
kuoeliassen/kuoeliassen_module.cp312-win_amd64.dll.a
kuoeliassen/kuoeliassen_module.cp312-win_amd64.pyd
kuoeliassen/utils.py
kuoeliassen/xarray_interface.py
kuoeliassen/__init__.py
kuoeliassen-0.2.3.dist-info/DELVEWHEEL
kuoeliassen-0.2.3.dist-info/METADATA
kuoeliassen-0.2.3.dist-info/RECORD
kuoeliassen-0.2.3.dist-info/WHEEL
kuoeliassen.libs/libgcc_s_seh-1-70a561105c0ab12e9e7fa7eeb237a93a.dll
kuoeliassen.libs/libgfortran-5-dfd5e8e44c757a41be7c7c401616f107.dll
kuoeliassen.libs/libgomp-1-adcc37ffd193cb17f3b01ddf417917a2.dll
kuoeliassen.libs/libquadmath-0-e044fa6e934d76e13834a4b23db9448b.dll
kuoeliassen.libs/libwinpthread-1-bbbb08e98392ba548f0d9435b69ed79e.dll
